LICENSE.md
README.md
setup.cfg
setup.py
ShellcodeFormatter/ShellcodeFormatter.py
ShellcodeFormatter/__init__.py
ShellcodeFormatter/definitions.py
ShellcodeFormatter/transformer.py
ShellcodeFormatter.egg-info/PKG-INFO
ShellcodeFormatter.egg-info/SOURCES.txt
ShellcodeFormatter.egg-info/dependency_links.txt
ShellcodeFormatter.egg-info/entry_points.txt
ShellcodeFormatter.egg-info/top_level.txt