Metadata-Version: 2.1
Name: ShellcodeFormatter
Version: 1.0.2
Summary: Transform binary shellcode into various formats
Home-page: https://github.com/eth0-re/ShellcodeFormatter
Author: Eth0
Author-email: e@eth0.re
License: UNKNOWN
Download-URL: https://github.com/eth0-re/ShellcodeFormatter/archive/refs/tags/v1.0.2.tar.gz
Platform: UNKNOWN
Classifier: Programming Language :: Python :: 3
Classifier: License :: OSI Approved :: MIT License
Classifier: Operating System :: OS Independent
License-File: LICENSE.md
